mt_excel/__init__.py
mt_excel/mt_excel.py
mt_excel/data/reviews-sample.xlsx
mt_excel-0.0.4.dist-info/LICENSE
mt_excel-0.0.4.dist-info/METADATA
mt_excel-0.0.4.dist-info/WHEEL
mt_excel-0.0.4.dist-info/top_level.txt
mt_excel-0.0.4.dist-info/RECORD
