Metadata-Version: 2.1
Name: mt_excel
Version: 0.0.4
Summary: A package for interacting with excel files
Home-page: 
Author: mole1000
Author-email: mole1000@protonmail.com
Classifier: Programming Language :: Python :: 3
Classifier: License :: OSI Approved :: MIT License
Classifier: Operating System :: OS Independent
Requires-Python: >=3.11
License-File: LICENSE
Requires-Dist: openpyxl>=3.1.3
Provides-Extra: testing
Requires-Dist: pytest; extra == "testing"
